{
  "kind": "singleType",
  "collectionName": "disclaimers",
  "info": {
    "singularName": "disclaimer",
    "pluralName": "disclaimers",
    "displayName": "Disclaimer"
  },
  "options": {
    "draftAndPublish": true
  },
  "pluginOptions": {},
  "attributes": {
    "Title": {
      "type": "text"
    },
    "Editor": {
      "type": "richtext"
    },
    "Meta_title": {
      "type": "text"
    },
    "Meta_description": {
      "type": "text"
    },
    "Featured_image": {
      "allowedTypes": [
        "images",
        "files",
        "videos",
        "audios"
      ],
      "type": "media",
      "multiple": false
    }
  }
}
