{
  "kind": "collectionType",
  "collectionName": "blogs",
  "info": {
    "singularName": "blog",
    "pluralName": "blogs",
    "displayName": "Blog",
    "description": ""
  },
  "options": {
    "draftAndPublish": true
  },
  "pluginOptions": {},
  "attributes": {
    "Title": {
      "type": "text"
    },
    "ClassicEditor": {
      "type": "richtext"
    },
    "Meta_title": {
      "type": "text"
    },
    "Meta_description": {
      "type": "text"
    },
    "Featured_image": {
      "type": "media",
      "multiple": false,
      "required": false,
      "allowedTypes": [
        "images",
        "files",
        "videos",
        "audios"
      ]
    },
    "Featured_image_url": {
      "type": "text"
    }
  }
}
